{
  "timestamp": "2025-05-19T23:17:00.598Z",
  "headers": {
    "accept": "*/*",
    "connection": "keep-alive",
    "content-length": "1133",
    "content-type": "application/json",
    "host": "dull-coins-judge.loca.lt",
    "signature": "v1 2fbdcfaf 1 MGQCMEcDUgyxE0eytJJGCxxMvJt+k6/klwvjELCkU8ouI5SFdqEz0bf7RDQpByUHCmwpVgIwepd/dU9xx3QQW+Mt5Yw1U3DxCUn95Mwkyn7V+3TxJtCOn/G9DZGbkmRlU3xUWpSh",
    "user-agent": "AHC/2.1",
    "x-forwarded-for": "77.75.153.78",
    "x-forwarded-host": "dull-coins-judge.loca.lt",
    "x-forwarded-port": "443",
    "x-forwarded-proto": "https, https"
  },
  "rawBody": "{\n  \"type\" : \"notification\",\n  \"event\" : \"payment.succeeded\",\n  \"object\" : {\n    \"id\" : \"2fbdcfab-000f-5000-b000-14e23341442d\",\n    \"status\" : \"succeeded\",\n    \"amount\" : {\n      \"value\" : \"4000.00\",\n      \"currency\" : \"RUB\"\n    },\n    \"income_amount\" : {\n      \"value\" : \"3860.00\",\n      \"currency\" : \"RUB\"\n    },\n    \"description\" : \"Подписка на 3 месяцев\",\n    \"recipient\" : {\n      \"account_id\" : \"1045209\",\n      \"gateway_id\" : \"2410174\"\n    },\n    \"payment_method\" : {\n      \"type\" : \"yoo_money\",\n      \"id\" : \"2fbdcfab-000f-5000-b000-14e23341442d\",\n      \"saved\" : false,\n      \"status\" : \"inactive\",\n      \"title\" : \"YooMoney wallet 410011758831136\",\n      \"account_number\" : \"410011758831136\"\n    },\n    \"captured_at\" : \"2025-05-19T23:17:03.413Z\",\n    \"created_at\" : \"2025-05-19T23:16:59.099Z\",\n    \"test\" : true,\n    \"refunded_amount\" : {\n      \"value\" : \"0.00\",\n      \"currency\" : \"RUB\"\n    },\n    \"paid\" : true,\n    \"refundable\" : true,\n    \"metadata\" : {\n      \"planId\" : \"1\",\n      \"speakerId\" : \"1\",\n      \"email\" : \"test123@test.ru\",\n      \"speakerDocumentId\" : \"qjiunkz1h2lq84pddqsq5vrh\"\n    }\n  }\n}"
}